database_smartools/__init__.py
database_smartools/database/__init__.py
database_smartools/database/dameng_extend.py
database_smartools/database/db_handler.py
database_smartools/database/mysql_extend.py
database_smartools/database/oceanbase_extend.py
database_smartools/database/oracle_extend.py
database_smartools/database/postgre_extend.py
database_smartools/database/sql_checker.py
database_smartools/utils/__init__.py
database_smartools/utils/config.py
database_smartools/utils/debug.py
database_smartools/utils/encrypt.py
database_smartools/utils/file.py
database_smartools/utils/http.py
database_smartools/utils/logger.py
database_smartools/utils/output.py
database_smartools/utils/sm4.py
database_smartools/utils/texter.py
database_smartools/utils/timer.py
database_smartools-0.0.4.dist-info/licenses/LICENSE
database_smartools-0.0.4.dist-info/METADATA
database_smartools-0.0.4.dist-info/WHEEL
database_smartools-0.0.4.dist-info/top_level.txt
database_smartools-0.0.4.dist-info/RECORD
