Metadata-Version: 2.4
Name: database-smartools
Version: 0.0.4
Summary: 数据库操作工具包
Home-page: 
Author: joelz
Author-email: zhongbj_26210@163.com
Requires-Python: >=3.11
License-File: LICENSE
Requires-Dist: altgraph==0.17.4
Requires-Dist: annotated-types==0.7.0
Requires-Dist: backports.tarfile==1.2.0
Requires-Dist: certifi==2025.8.3
Requires-Dist: cffi==2.0.0
Requires-Dist: charset-normalizer==3.4.3
Requires-Dist: cryptography==45.0.7
Requires-Dist: DBUtils==3.1.2
Requires-Dist: dmPython==2.5.22
Requires-Dist: docutils==0.22
Requires-Dist: greenlet==3.2.4
Requires-Dist: id==1.5.0
Requires-Dist: idna==3.10
Requires-Dist: importlib_metadata==8.7.0
Requires-Dist: jaraco.classes==3.4.0
Requires-Dist: jaraco.context==6.0.1
Requires-Dist: jaraco.functools==4.3.0
Requires-Dist: JayDeBeApi==1.2.3
Requires-Dist: jpype1==1.5.2
Requires-Dist: keyring==25.6.0
Requires-Dist: markdown-it-py==4.0.0
Requires-Dist: mdurl==0.1.2
Requires-Dist: more-itertools==10.8.0
Requires-Dist: mysql-connector-python==9.4.0
Requires-Dist: nh3==0.3.0
Requires-Dist: numpy==2.3.3
Requires-Dist: oracledb==3.3.0
Requires-Dist: packaging==25.0
Requires-Dist: pandas==2.3.2
Requires-Dist: pefile==2023.2.7
Requires-Dist: psycopg2-binary==2.9.10
Requires-Dist: pycparser==2.23
Requires-Dist: pydantic==2.11.7
Requires-Dist: pydantic_core==2.33.2
Requires-Dist: Pygments==2.19.2
Requires-Dist: pyinstaller==6.15.0
Requires-Dist: pyinstaller-hooks-contrib==2025.8
Requires-Dist: python-dateutil==2.9.0.post0
Requires-Dist: pytz==2025.2
Requires-Dist: pywin32-ctypes==0.2.3
Requires-Dist: readme_renderer==44.0
Requires-Dist: requests==2.32.5
Requires-Dist: requests-toolbelt==1.0.0
Requires-Dist: rfc3986==2.0.0
Requires-Dist: rich==14.1.0
Requires-Dist: six==1.17.0
Requires-Dist: SQLAlchemy==2.0.43
Requires-Dist: twine==6.2.0
Requires-Dist: typing-inspection==0.4.1
Requires-Dist: typing_extensions==4.15.0
Requires-Dist: tzdata==2025.2
Requires-Dist: urllib3==2.5.0
Requires-Dist: zipp==3.23.0
Dynamic: author
Dynamic: author-email
Dynamic: description
Dynamic: description-content-type
Dynamic: license-file
Dynamic: requires-dist
Dynamic: requires-python
Dynamic: summary
